osol/__init__.py
osol/algorithms/__init__.py
osol/algorithms/abstract.py
osol/algorithms/benchmarks.py
osol/algorithms/big_bang_big_crunch.py
osol/algorithms/black_hole_optimization.py
osol/algorithms/numerical_gradient_descent.py
osol/algorithms/random_search.py
osol/tools/__init__.py
osol/tools/coding.py
osol/tools/testing.py
osol/tools/vectors.py
osol-0.0.10.dist-info/WHEEL
osol-0.0.10.dist-info/METADATA
osol-0.0.10.dist-info/RECORD
