Metadata-Version: 2.1
Name: osol
Version: 0.0.10
Summary: 
License: MIT
Author: wol4aravio
Author-email: panovskiy.v@yandex.ru
Requires-Python: >=3.8.0,<3.9.0
Classifier: License :: OSI Approved :: MIT License
Classifier: Programming Language :: Python :: 3
Classifier: Programming Language :: Python :: 3.8
Requires-Dist: numpy (>=1.20.2,<2.0.0)
Requires-Dist: scipy (>=1.6.2,<2.0.0)
